LICENSE
MANIFEST.in
README.rst
setup.py
helga_spook/__init__.py
helga_spook/plugin.py
helga_spook/spook.lines
helga_spook.egg-info/PKG-INFO
helga_spook.egg-info/SOURCES.txt
helga_spook.egg-info/dependency_links.txt
helga_spook.egg-info/entry_points.txt
helga_spook.egg-info/top_level.txt
helga_spook.egg-info/zip-safe