Metadata-Version: 1.1
Name: helga-spook
Version: 1.1.5
Summary: prints nsa buzzwords
Home-page: https://github.com/michaelorr/helga-spook
Author: Michael Orr
Author-email: michael@orr.co
License: LICENSE
Keywords: irc bot nsa spook emacs
Platform: UNKNOWN
Classifier: Development Status :: 4 - Beta
Classifier: License :: OSI Approved :: GNU General Public License v3 (GPLv3)
Classifier: Operating System :: OS Independent
Classifier: Programming Language :: Python
Classifier: Topic :: Software Development :: Libraries :: Python Modules
Classifier: Topic :: Communications :: Chat :: Internet Relay Chat
